MANIFEST.in
README.txt
setup.cfg
setup.py
XStatic_OpenSans.egg-info/PKG-INFO
XStatic_OpenSans.egg-info/SOURCES.txt
XStatic_OpenSans.egg-info/dependency_links.txt
XStatic_OpenSans.egg-info/namespace_packages.txt
XStatic_OpenSans.egg-info/not-zip-safe
XStatic_OpenSans.egg-info/top_level.txt
xstatic/__init__.py
xstatic/pkg/__init__.py
xstatic/pkg/opensans/__init__.py
xstatic/pkg/opensans/data/fonts/Bold/OpenSans-Bold.eot
xstatic/pkg/opensans/data/fonts/Bold/OpenSans-Bold.svg
xstatic/pkg/opensans/data/fonts/Bold/OpenSans-Bold.ttf
xstatic/pkg/opensans/data/fonts/Bold/OpenSans-Bold.woff
xstatic/pkg/opensans/data/fonts/Bold/OpenSans-Bold.woff2
xstatic/pkg/opensans/data/fonts/BoldItalic/OpenSans-BoldItalic.eot
xstatic/pkg/opensans/data/fonts/BoldItalic/OpenSans-BoldItalic.svg
xstatic/pkg/opensans/data/fonts/BoldItalic/OpenSans-BoldItalic.ttf
xstatic/pkg/opensans/data/fonts/BoldItalic/OpenSans-BoldItalic.woff
xstatic/pkg/opensans/data/fonts/BoldItalic/OpenSans-BoldItalic.woff2
xstatic/pkg/opensans/data/fonts/ExtraBold/OpenSans-ExtraBold.eot
xstatic/pkg/opensans/data/fonts/ExtraBold/OpenSans-ExtraBold.svg
xstatic/pkg/opensans/data/fonts/ExtraBold/OpenSans-ExtraBold.ttf
xstatic/pkg/opensans/data/fonts/ExtraBold/OpenSans-ExtraBold.woff
xstatic/pkg/opensans/data/fonts/ExtraBold/OpenSans-ExtraBold.woff2
xstatic/pkg/opensans/data/fonts/ExtraBoldItalic/OpenSans-ExtraBoldItalic.eot
xstatic/pkg/opensans/data/fonts/ExtraBoldItalic/OpenSans-ExtraBoldItalic.svg
xstatic/pkg/opensans/data/fonts/ExtraBoldItalic/OpenSans-ExtraBoldItalic.ttf
xstatic/pkg/opensans/data/fonts/ExtraBoldItalic/OpenSans-ExtraBoldItalic.woff
xstatic/pkg/opensans/data/fonts/ExtraBoldItalic/OpenSans-ExtraBoldItalic.woff2
xstatic/pkg/opensans/data/fonts/Italic/OpenSans-Italic.eot
xstatic/pkg/opensans/data/fonts/Italic/OpenSans-Italic.svg
xstatic/pkg/opensans/data/fonts/Italic/OpenSans-Italic.ttf
xstatic/pkg/opensans/data/fonts/Italic/OpenSans-Italic.woff
xstatic/pkg/opensans/data/fonts/Italic/OpenSans-Italic.woff2
xstatic/pkg/opensans/data/fonts/Light/OpenSans-Light.eot
xstatic/pkg/opensans/data/fonts/Light/OpenSans-Light.svg
xstatic/pkg/opensans/data/fonts/Light/OpenSans-Light.ttf
xstatic/pkg/opensans/data/fonts/Light/OpenSans-Light.woff
