Metadata-Version: 1.0
Name: XStatic-OpenSans
Version: 1.0.0
Summary: OpenSans 1.0 (XStatic packaging standard)
Home-page: https://fonts.google.com/specimen/Open+Sans
Author: Frederic Peters
Author-email: fpeters@entrouvert.com
License: (same as OpenSans)
Keywords: opensans xstatic
Platform: any
